{
  "topicId": "capstone-automation-project",
  "repairs": [
    {
      "code": "PYTHON_SKETCH_LINE_BY_LINE_EXPLANATION_ADDED",
      "category": "text",
      "severity": "medium",
      "field": "sketchBlocks.capstone-test-polish.bodyMarkdown",
      "message": "Added a short line-by-line explanation after a multi-line code example."
    },
    {
      "code": "PYTHON_POLICY_EXTRA_EXERCISE_DROPPED",
      "category": "other",
      "severity": "medium",
      "field": "capstone-step-3-summary-functions",
      "message": "Dropped extra fill_blank_choice exercise to satisfy the planned exercise mix for \"capstone-automation-project\"."
    },
    {
      "code": "PYTHON_POLICY_EXERCISE_SYNTHESIZED",
      "category": "other",
      "severity": "medium",
      "field": "policy_code_input_1",
      "message": "Added a fallback code_input exercise to satisfy the planned exercise mix for \"capstone-automation-project\"."
    }
  ]
}