{
  "topicId": "databases-overview",
  "subjectSlug": "sql",
  "moduleSlug": "sql_module_0",
  "sectionSlug": "section_0_1",
  "prefix": "sql0",
  "minutes": 20,
  "topic": {
    "labelKey": "topics.sql.sql_module_0.databases-overview.label",
    "summaryKey": "topics.sql.sql_module_0.databases-overview.summary"
  },
  "cards": [
    {
      "id": "sketch0",
      "kind": "sketch",
      "titleKey": "topics.sql.sql_module_0.databases-overview.cards.sketch0.title",
      "sketchId": "sketch-what-is-database",
      "height": 420
    },
    {
      "id": "sketch1",
      "kind": "sketch",
      "titleKey": "topics.sql.sql_module_0.databases-overview.cards.sketch1.title",
      "sketchId": "sketch-how-data-organized",
      "height": 420
    },
    {
      "id": "quiz",
      "kind": "quiz",
      "titleKey": "topics.sql.sql_module_0.databases-overview.cards.quiz.title",
      "quiz": {
        "difficulty": "easy",
        "n": 4,
        "allowReveal": true,
        "preferKind": null,
        "maxAttempts": 10
      }
    }
  ],
  "sketches": [
    {
      "id": "sketch-what-is-database",
      "archetype": "paragraph",
      "titleKey": "sketches.sql.sql_module_0.databases-overview.sketch-what-is-database.title",
      "bodyKey": "sketches.sql.sql_module_0.databases-overview.sketch-what-is-database.bodyMarkdown"
    },
    {
      "id": "sketch-how-data-organized",
      "archetype": "paragraph",
      "titleKey": "sketches.sql.sql_module_0.databases-overview.sketch-how-data-organized.title",
      "bodyKey": "sketches.sql.sql_module_0.databases-overview.sketch-how-data-organized.bodyMarkdown"
    }
  ],
  "exercises": [
    {
      "id": "quiz-define-database",
      "kind": "single_choice",
      "purpose": "quiz",
      "weight": 1,
      "messageBase": "quiz.quiz-define-database",
      "optionIds": [
        "a",
        "b",
        "c",
        "d"
      ],
      "expected": {
        "kind": "single_choice",
        "optionId": "a"
      }
    },
    {
      "id": "quiz-data-organization",
      "kind": "single_choice",
      "purpose": "quiz",
      "weight": 1,
      "messageBase": "quiz.quiz-data-organization",
      "optionIds": [
        "a",
        "b",
        "c",
        "d"
      ],
      "expected": {
        "kind": "single_choice",
        "optionId": "a"
      }
    },
    {
      "id": "quiz-table-components",
      "kind": "multi_choice",
      "purpose": "quiz",
      "weight": 1,
      "messageBase": "quiz.quiz-table-components",
      "optionIds": [
        "a",
        "b",
        "c",
        "d"
      ],
      "expected": {
        "kind": "multi_choice",
        "optionIds": []
      }
    },
    {
      "id": "quiz-table-order",
      "kind": "drag_reorder",
      "purpose": "quiz",
      "weight": 1,
      "messageBase": "quiz.quiz-table-order",
      "tokenIds": [
        "t1",
        "t2",
        "t3",
        "t4"
      ],
      "expected": {
        "kind": "drag_reorder",
        "tokenIds": [
          "t1",
          "t2",
          "t3",
          "t4"
        ]
      }
    },
    {
      "id": "quiz-sql-table-query",
      "kind": "code_input",
      "purpose": "quiz",
      "weight": 1,
      "messageBase": "quiz.quiz-sql-table-query",
      "language": "sql",
      "fixedSqlDialect": "sqlite",
      "recipe": {
        "type": "sql_query",
        "datasetId": "products_catalog",
        "resultShape": "table",
        "solutionCode": "SELECT * FROM products;"
      }
    }
  ]
}
